CONTRIBUTING.md
MANIFEST.in
README.rst
setup.py
docs/HISTORY.txt
docs/LICENSE.GPL
docs/LICENSE.txt
eea/__init__.py
eea.relations.egg-info/PKG-INFO
eea.relations.egg-info/SOURCES.txt
eea.relations.egg-info/dependency_links.txt
eea.relations.egg-info/entry_points.txt
eea.relations.egg-info/namespace_packages.txt
eea.relations.egg-info/not-zip-safe
eea.relations.egg-info/requires.txt
eea.relations.egg-info/top_level.txt
eea/relations/README.rst
eea/relations/README.txt
eea/relations/__init__.py
eea/relations/config.py
eea/relations/configure.zcml
eea/relations/i18nize
eea/relations/interfaces.py
eea/relations/meta.zcml
eea/relations/overrides.zcml
eea/relations/profiles.zcml
eea/relations/setuphandlers.py
eea/relations/skins.zcml
eea/relations/version.txt
eea/relations/Extensions/install.py
eea/relations/async/__init__.py
eea/relations/async/configure.zcml
eea/relations/async/subscribers.py
eea/relations/browser/__init__.py
eea/relations/browser/configure.zcml
eea/relations/browser/interfaces.py
eea/relations/browser/app/__init__.py
eea/relations/browser/app/badrelations.py
eea/relations/browser/app/graph.py
eea/relations/browser/app/macro.py
eea/relations/browser/app/popup.py
eea/relations/browser/app/tool.py
eea/relations/browser/app/viewlets.py
eea/relations/browser/css/tool.css
eea/relations/browser/js/tool.js
eea/relations/browser/template/badrelations.pt
eea/relations/browser/template/contenttype.pt
eea/relations/browser/template/contenttypes.pt
eea/relations/browser/template/default.xml
eea/relations/browser/template/popup-selecteditem.pt
eea/relations/browser/template/popup-selecteditems.pt
eea/relations/browser/template/popup.pt
eea/relations/browser/template/query.pt
eea/relations/browser/template/relation.pt
eea/relations/browser/template/relation_status.pt
eea/relations/browser/template/relations.pt
eea/relations/browser/template/tool.pt
eea/relations/component/__init__.py
eea/relations/component/configure.zcml
eea/relations/component/contenttype.py
eea/relations/component/interfaces.py
eea/relations/component/relation.py
eea/relations/content/__init__.py
eea/relations/content/configure.zcml
eea/relations/content/contenttype.py
eea/relations/content/interfaces.py
eea/relations/content/relation.py
eea/relations/content/tool.gif
eea/relations/content/tool.py
