Metadata-Version: 2.1
Name: eea.relations
Version: 12.3
Summary: EEA Possible Relations. This package provides a flexible way to manage relations in a Plone site. it provides a new reference browser widget and a central management interface for relations, their labels and requirements.
Home-page: https://github.com/collective/eea.relations
Author: European Environment Agency: IDM2 A-Team
Author-email: eea-edw-a-team-alerts@googlegroups.com
License: GPL
Keywords: EEA Add-ons Plone Zope
Platform: UNKNOWN
Classifier: Framework :: Zope2
Classifier: Framework :: Plone
Classifier: Framework :: Plone :: 4.0
Classifier: Framework :: Plone :: 4.1
Classifier: Framework :: Plone :: 4.2
Classifier: Framework :: Plone :: 4.3
Classifier: Programming Language :: Zope
Classifier: Programming Language :: Python
Classifier: Programming Language :: Python :: 2.7
Classifier: Topic :: Software Development :: Libraries :: Python Modules
Classifier: License :: OSI Approved :: GNU General Public License (GPL)
Provides-Extra: test
Provides-Extra: yum
Provides-Extra: apt
